MANIFEST.in
README.md
setup.py
etc/colab/plugins.d/mkdocs-tos.py
src/colab_mkdocs_tos/__init__.py
src/colab_mkdocs_tos/diazo.xml
src/colab_mkdocs_tos/models.py
src/colab_mkdocs_tos/urls.py
src/colab_mkdocs_tos/views.py
src/colab_mkdocs_tos.egg-info/PKG-INFO
src/colab_mkdocs_tos.egg-info/SOURCES.txt
src/colab_mkdocs_tos.egg-info/dependency_links.txt
src/colab_mkdocs_tos.egg-info/not-zip-safe
src/colab_mkdocs_tos.egg-info/requires.txt
src/colab_mkdocs_tos.egg-info/top_level.txt
src/colab_mkdocs_tos/management/__init__.py
src/colab_mkdocs_tos/management/commands/__init__.py
src/colab_mkdocs_tos/management/commands/build_mkdocs.py
src/colab_mkdocs_tos/management/commands/generate_mkdocs_config.py
src/colab_mkdocs_tos/mkdocs_pages/audiencias.md
src/colab_mkdocs_tos/mkdocs_pages/expressao.md
src/colab_mkdocs_tos/mkdocs_pages/index.md
src/colab_mkdocs_tos/mkdocs_pages/tos.md
src/colab_mkdocs_tos/mkdocs_pages/wikilegis.md
src/colab_mkdocs_tos/mkdocs_pages/images/audiencias1.png
src/colab_mkdocs_tos/mkdocs_pages/images/edemocracia1.png
src/colab_mkdocs_tos/mkdocs_pages/images/expressao1.png
src/colab_mkdocs_tos/mkdocs_pages/images/expressao2.png
src/colab_mkdocs_tos/mkdocs_pages/images/expressao3.png
src/colab_mkdocs_tos/mkdocs_pages/images/expressao4.png
src/colab_mkdocs_tos/mkdocs_pages/images/wikilegis1.png
src/colab_mkdocs_tos/mkdocs_pages/stylesheets/extra.css
src/colab_mkdocs_tos/static/scss/overrides-tos.scss
src/colab_mkdocs_tos/templates/mkdocs.yml
src/colab_mkdocs_tos/templates/proxy/mkdocs.html
src/colab_mkdocs_tos/theme/partials/language.html