Metadata-Version: 1.1
Name: colab-mkdocs-tos
Version: 0.2.0
Summary: Colab Mkdocs Plugin
Home-page: https://github.com/labhackercd/colab-mkdocs-plugin
Author: labhackercd
Author-email: labhackercd@gmail.com
License: GPLv3
Platform: UNKNOWN
Classifier: Framework :: Django
Classifier: Intended Audience :: Developers
Classifier: Intended Audience :: System Administrators
Classifier: Operating System :: OS Independent
Classifier: Topic :: Software Development
